README.txt
setup.py
pyvalidate/__init__.py
pyvalidate/pyvalidate.py
pyvalidate.egg-info/PKG-INFO
pyvalidate.egg-info/SOURCES.txt
pyvalidate.egg-info/dependency_links.txt
pyvalidate.egg-info/top_level.txt