Metadata-Version: 1.1
Name: pyvalidate
Version: 1.3.1
Summary: Python method's parameter validation library, as a pythonic decorator
Home-page: http://packages.python.org/pyvalidate
Author: Vahid Mardani
Author-email: vahid.mardani@gmail.com
License: UNKNOWN
Platform: any
Classifier: Development Status :: 5 - Production/Stable
Classifier: License :: Freeware
Classifier: Intended Audience :: Developers
Classifier: Operating System :: OS Independent
Classifier: Programming Language :: Python :: 2.6
Classifier: Programming Language :: Python :: 2.7
Classifier: Topic :: Software Development :: Libraries
